mountainlab_pytools/__init__.py
mountainlab_pytools/mdaio/__init__.py
mountainlab_pytools/mdaio/mdaio_impl.py
mountainlab_pytools/mlproc/__init__.py
mountainlab_pytools/mlproc/mlclient.py
mountainlab_pytools/mlproc/mljobmonitor.js
mountainlab_pytools/mlproc/mljobmonitor.py
mountainlab_pytools/mlproc/mlproc_impl.py
mountainlab_pytools/mlprocessors/__init__.py
mountainlab_pytools/mlprocessors/core.py
mountainlab_pytools/mlprocessors/registry.py
mountainlab_pytools/mlprocessors/validators.py
mountainlab_pytools/processormanager/__init__.py
mountainlab_pytools/processormanager/docscrape.py
mountainlab_pytools/processormanager/processormanager_impl.py
mountainlab_pytools-0.7.5.dist-info/LICENSE
mountainlab_pytools-0.7.5.dist-info/METADATA
mountainlab_pytools-0.7.5.dist-info/WHEEL
mountainlab_pytools-0.7.5.dist-info/top_level.txt
mountainlab_pytools-0.7.5.dist-info/RECORD
