Metadata-Version: 2.1
Name: mountainlab-pytools
Version: 0.7.5
Summary: Tools for using MountainLab with python
Home-page: https://github.com/magland/mountainlab_pytools
Author: Jeremy Magland
Author-email: jmagland@flatironinstitute.org
License: UNKNOWN
Platform: UNKNOWN
Classifier: Programming Language :: Python :: 3
Classifier: License :: OSI Approved :: Apache Software License
Classifier: Operating System :: OS Independent
Requires-Dist: requests
Requires-Dist: numpy
Requires-Dist: numpydoc
Requires-Dist: ipython
Requires-Dist: vdom
Requires-Dist: ipywidgets
Requires-Dist: jp-proxy-widget
